{
  "id": 33309,
  "name": "Virgil Tibbs (G14)",
  "generation": 14,
  "created_at": "2017-12-02T23:05:40.000Z",
  "birthday": "2017-12-02T00:00:00.000Z",
  "color": "sizzurp",
  "bio": "Good morning! My name's Virgil Tibbs (G14). I once peed on Cleopatra's cat. They had it coming. It wasn't heavily publicized, but I once had a brief relationship with Puss in Boots. Will you be the garlic butter to my wasabi?",
  "language": "en",
  "matron": "32746@11",
  "sire": "16624@13",
  "children": [
    "35831@15",
    "50124@15",
    "70289@15"
  ],
  "hatched": true,
  "wrapped": false
}