{
  "id": 327059,
  "name": "My Pussy Loves You",
  "generation": 12,
  "created_at": "2017-12-15T17:11:56.000Z",
  "birthday": "2017-12-15T00:00:00.000Z",
  "color": "gold",
  "bio": "Uh, hi! My name's My Pussy Loves You. I once peed on Mother Theresa's cat. They had it coming. I put marmalade on everything. Like, everything: hot dogs, steak—everything! Can you make my ridiculous dreams come true?",
  "kitty_type": "fancy",
  "is_fancy": true,
  "fancy_type": "Mistletoe",
  "language": "en",
  "matron": "281472@10",
  "sire": "296374@11",
  "children": [
    "335760@13",
    "340321@13",
    "347294@13",
    "375686@17",
    "376837@23",
    "380314@16",
    "393483@13",
    "415798@13",
    "452742@13"
  ],
  "hatched": true,
  "wrapped": false,
  "fancy_ranking": 546,
  "fancy_limit": 2000,
  "fancy_remaining": 0
}