{
  "id": 24288,
  "name": "Flat-earth NASA Kitty",
  "generation": 20,
  "created_at": "2017-12-01T20:32:24.000Z",
  "birthday": "2017-12-01T00:00:00.000Z",
  "color": "mintgreen",
  "bio": "Good morning! I'm Flat-earth NASA Kitty. I want to live in a world where people believe the world is flat. I was voted most likely to work at NASA in college. We can be friends, but keep the ultra purrsonal stuff to yourself, please.",
  "language": "en",
  "matron": "18806@19",
  "sire": "4013@9",
  "children": [
    "94861@21",
    "191919@21"
  ],
  "hatched": true,
  "wrapped": false
}