{
  "id": 24365,
  "name": "Maneki-neko😻 | cerulian",
  "generation": 6,
  "created_at": "2017-12-01T20:45:03.000Z",
  "birthday": "2017-12-01T00:00:00.000Z",
  "color": "mintgreen",
  "bio": "Good day! I'm Maneki-neko😻 | cerulian. I'm a Aerobics Athlete  by day, and I like playing chess by night. I once made a labradoodle jump. Will you be the marmalade to my cinammon?",
  "language": "en",
  "matron": "23957@5",
  "sire": "22704@5",
  "children": [
    "24534@7",
    "25052@7",
    "28466@7",
    "46519@7",
    "104177@7",
    "108539@11",
    "126105@7",
    "154042@7",
    "216427@7",
    "314791@7"
  ],
  "hatched": true,
  "wrapped": false
}