{
  "id": 260533,
  "name": "OkieDokieArtichokie",
  "generation": 5,
  "created_at": "2017-12-12T04:04:57.000Z",
  "birthday": "2017-12-12T00:00:00.000Z",
  "color": "chestnut",
  "bio": "Mahalo! I'm OkieDokieArtichokie. I've never told anyone this, but I once pranced with a dog. I once dreamed of being a Dogwalker. Now I can be found summoning ghosts all day. In time you'll learn how purrfect I am.",
  "kitty_type": "fancy",
  "is_fancy": true,
  "fancy_type": "ShipCat",
  "language": "en",
  "matron": "231017@4",
  "sire": "259689@3",
  "children": [

  ],
  "hatched": true,
  "wrapped": false,
  "fancy_ranking": 687,
  "fancy_limit": 2000,
  "fancy_remaining": 0
}