{
  "id": 27106,
  "name": "Gen 3 | Swift",
  "generation": 3,
  "created_at": "2017-12-02T05:58:37.000Z",
  "birthday": "2017-12-02T00:00:00.000Z",
  "color": "limegreen",
  "bio": "*hissing noises*! I'm Gen 3 | Swift. In high school, I was voted school jock. Sometimes I daydream of a life full of reciting poetry, cantaloupe, and swiping right. Will you be the marmalade to my maple syrup?",
  "language": "en",
  "matron": "22094@2",
  "sire": "21504@2",
  "children": [
    "31272@4",
    "31923@4",
    "32144@4",
    "32638@4",
    "33439@4",
    "34804@4",
    "37356@4",
    "44242@4",
    "71472@4",
    "120457@4"
  ],
  "hatched": true,
  "wrapped": false
}