{
  "id": 27760,
  "name": "Peach Luckystripe",
  "generation": 7,
  "created_at": "2017-12-02T08:11:01.000Z",
  "birthday": "2017-12-02T00:00:00.000Z",
  "color": "mintgreen",
  "bio": "Aloha! I'm Peach Luckystripe. I'm a professional Aerobics Athlete  and I love lasagna. When no one's home, I invite my pals over and we listen to Gloria Estefan. I like your face.",
  "language": "en",
  "matron": "27663@1",
  "sire": "27735@6",
  "children": [
    "60372@8"
  ],
  "hatched": true,
  "wrapped": false
}