{
  "id": 27845,
  "name": "g14 royal lucky",
  "generation": 14,
  "created_at": "2017-12-02T08:33:57.000Z",
  "birthday": "2017-12-02T00:00:00.000Z",
  "color": "strawberry",
  "bio": "Good morning! I'm g14 royal lucky. I want to live in a world where people believe the world is flat. In my free time, I can usually be found gullible or pole dancing. I hope you like kitten around as much as I do!",
  "language": "en",
  "matron": "12445@13",
  "sire": "17581@3",
  "children": [
    "34175@15",
    "41401@15",
    "60246@16",
    "147755@17"
  ],
  "hatched": true,
  "wrapped": false
}