{
  "id": 1190,
  "name": "Abby",
  "generation": 0,
  "created_at": "2017-11-23T09:50:24.000Z",
  "birthday": "2017-11-23T00:00:00.000Z",
  "color": "strawberry",
  "bio": "Yo! I'm Abby. My friends describe me as seductive and ridiculous. I'm convinced that the world is flat. One day I'll prove it. I think you'll love me beclaws I have cattitude.",
  "language": "en",
  "matron": null,
  "sire": null,
  "children": [
    "3556@1",
    "122354@1",
    "128867@1",
    "129480@1",
    "130448@1",
    "133073@1",
    "139778@1",
    "153633@1",
    "169339@1",
    "187897@1",
    "221297@1",
    "277230@1",
    "351205@1",
    "403917@1",
    "441404@1",
    "489987@1",
    "500417@1",
    "530424@1"
  ],
  "hatched": true,
  "wrapped": false
}