{
  "id": 1392,
  "name": "Captain Ahab",
  "generation": 0,
  "created_at": "2017-11-23T10:24:22.000Z",
  "birthday": "2017-11-23T00:00:00.000Z",
  "color": "topaz",
  "bio": "Oh hi! Captain Ahab here. I'm here to enjoy tripping my owner and eating lasagna. It wasn't heavily publicized, but I once had a brief relationship with Cheshire Cat. Can you make my seductive dreams come true?",
  "language": "en",
  "matron": null,
  "sire": null,
  "children": [
    "3319@4",
    "3428@3",
    "3445@4",
    "3497@1",
    "13075@1",
    "13337@10",
    "13827@12",
    "14842@5",
    "22788@15",
    "31922@16",
    "35288@9",
    "101282@1",
    "202549@1",
    "431382@2",
    "467401@1",
    "477665@6",
    "493156@1",
    "505827@1",
    "525893@1",
    "551001@1",
    "588841@1",
    "623106@8",
    "638936@1",
    "656981@1",
    "678001@1",
    "700140@1",
    "715352@1",
    "742596@1",
    "785746@1",
    "792792@1",
    "863275@1",
    "881304@1",
    "919961@1",
    "984518@1",
    "1038347@1",
    "1096196@1",
    "1143550@1",
    "1166001@1",
    "1205630@1",
    "1271658@1",
    "1314261@2",
    "1342479@1",
    "1378708@1",
    "1389339@16",
    "1479544@1",
    "1506251@1",
    "1619479@1",
    "1675790@1",
    "1683968@1",
    "1763808@1",
    "1960243@1",
    "1969834@1"
  ],
  "hatched": true,
  "wrapped": true
}