{
  "id": 26723,
  "name": "Clawdia",
  "generation": 20,
  "created_at": "2017-12-02T04:38:32.000Z",
  "birthday": "2017-12-02T00:00:00.000Z",
  "color": "sizzurp",
  "bio": "Aloha! I'm Clawdia. I'm a professional Dispensary Clerk and I love steak. I am 74% oracle, 80% Dispensary Clerk, and otherwise bad at math. I look forward to reciting poetry with you.",
  "language": "en",
  "matron": "19580@18",
  "sire": "21444@19",
  "children": [
    "59926@21",
    "133575@21"
  ],
  "hatched": true,
  "wrapped": false
}