{
  "id": 30115,
  "name": "Best start(moneymaker)",
  "generation": 15,
  "created_at": "2017-12-02T15:51:17.000Z",
  "birthday": "2017-12-02T00:00:00.000Z",
  "color": "topaz",
  "bio": "Aloha! I'm Best start(moneymaker). In high school, I was voted most likely to work at NASA. My great-great-great-great-great-great grandkitty lived with Marie Antoinette. Let's pawty!",
  "language": "en",
  "matron": "19804@11",
  "sire": "20096@14",
  "children": [
    "74692@21",
    "90260@18",
    "114094@16",
    "128720@17",
    "183358@17",
    "269462@16"
  ],
  "hatched": true,
  "wrapped": false
}