{
  "id": 4228,
  "name": "Tiger",
  "generation": 12,
  "created_at": "2017-11-24T06:19:53.000Z",
  "birthday": "2017-11-24T00:00:00.000Z",
  "color": "sizzurp",
  "bio": "Oh hi! I'm Tiger. In high school, I was voted school jock. My friends describe me as \"fabulous.\" It's... accurate. I look forward to reciting poetry with you.",
  "language": "en",
  "matron": "3796@5",
  "sire": "3937@11",
  "children": [
    "4532@14",
    "4890@14",
    "6043@14",
    "69034@18"
  ],
  "hatched": true,
  "wrapped": false
}