{
  "id": 4640,
  "name": "⭐️ Starry",
  "generation": 3,
  "created_at": "2017-11-24T09:27:44.000Z",
  "birthday": "2017-11-24T00:00:00.000Z",
  "color": "sizzurp",
  "bio": "Yo! I'm ⭐️ Starry. I want to live in a world where people believe that one day cats will rule this planet. I once dreamed of being a Aerobics Athlete . Now I can be found watching reality tv all day. I like your face.",
  "language": "en",
  "matron": "3112@2",
  "sire": "3293@1",
  "children": [
    "5229@12",
    "5263@12",
    "5633@11",
    "9265@12",
    "22773@11",
    "30571@14",
    "71656@14"
  ],
  "hatched": true,
  "wrapped": false
}