{
  "id": 13289,
  "name": "Gen 2 | CryptoSapphire",
  "generation": 2,
  "created_at": "2017-11-29T21:30:06.000Z",
  "birthday": "2017-11-29T00:00:00.000Z",
  "color": "sizzurp",
  "bio": "Yo! I'm Gen 2 | CryptoSapphire. I enjoy shakin' dat booty, chasing string, and slappin' da bass. My great-great-great-great-great-great grandkitty lived with Confucius. I look forward to licking doorknobs with you.",
  "language": "en",
  "matron": "10783@1",
  "sire": "11799@1",
  "children": [
    "13303@4",
    "13342@4",
    "13539@4",
    "13705@13",
    "14131@3",
    "65042@3",
    "74327@3",
    "89748@3",
    "126212@3",
    "153158@3"
  ],
  "hatched": true,
  "wrapped": false
}