{
  "id": 13848,
  "name": null,
  "generation": 19,
  "created_at": "2017-11-29T23:52:27.000Z",
  "birthday": "2017-11-29T00:00:00.000Z",
  "color": "strawberry",
  "bio": "Hey cutie! I'm Kitty #13848. I'm a Spin Instructor  by day, and I like summoning ghosts by night. It wasn't heavily publicized, but I once had a brief relationship with Cheshire Cat. We're so fur-tunate to have found each other!",
  "language": "en",
  "matron": "6827@10",
  "sire": "13246@18",
  "children": [
    "92619@20"
  ],
  "hatched": true,
  "wrapped": false
}