{
  "id": 19350,
  "name": "Wanna be birdie",
  "generation": 15,
  "created_at": "2017-11-30T21:53:09.000Z",
  "birthday": "2017-11-30T00:00:00.000Z",
  "color": "mintgreen",
  "bio": "Oh hi! Wanna be birdie here. I'm here to enjoy taking selfies and reading garfield. My great-great-great-great-great-great grandkitty lived with Martin Luther King Jr.. Our friendship will be vegan, ridiculous, and full of ice cream.",
  "language": "en",
  "matron": "17724@14",
  "sire": "17908@5",
  "children": [
    "20773@16",
    "21706@16",
    "28062@16",
    "53085@16"
  ],
  "hatched": true,
  "wrapped": false
}