{
  "id": 10552,
  "name": null,
  "generation": 14,
  "created_at": "2017-11-29T00:49:00.000Z",
  "birthday": "2017-11-29T00:00:00.000Z",
  "color": "mintgreen",
  "bio": "Sup playa! I'm Kitty #10552. I'm often referred to as the Bart Simpson of the group. Sometimes I daydream of a life full of eating lasagna, salad, and jump-roping. Let's pawty!",
  "language": "en",
  "matron": "8954@13",
  "sire": "8518@11",
  "children": [
    "52279@18",
    "88619@20",
    "161334@20",
    "321282@20",
    "831159@20",
    "1647203@20",
    "1665059@20",
    "1673021@20",
    "1676165@20",
    "1696672@20"
  ],
  "hatched": true,
  "wrapped": true
}