{
  "id": 10623,
  "name": null,
  "generation": 17,
  "created_at": "2017-11-29T01:30:19.000Z",
  "birthday": "2017-11-29T00:00:00.000Z",
  "color": "strawberry",
  "bio": "Sup playa! Kitty #10623 here. I'm here to enjoy licking doorknobs and tripping my owner. Some people say I'm the Cersei Lannister of the group. Our friendship will be fabulous, prickly, and full of ice cream.",
  "language": "en",
  "matron": "8479@16",
  "sire": "8924@15",
  "children": [
    "12326@18",
    "16517@18",
    "37957@18",
    "44725@18"
  ],
  "hatched": true,
  "wrapped": false
}