{
  "id": 10958,
  "name": "Mirri | G1",
  "generation": 1,
  "created_at": "2017-11-29T04:25:29.000Z",
  "birthday": "2017-11-29T00:00:00.000Z",
  "color": "topaz",
  "bio": "Sup playa! I'm Mirri | G1. My friends describe me as gorgeous and prickly. I would give it all up to be on Oprah. Will you be the marmalade to my pickles?",
  "language": "en",
  "matron": "10616@0",
  "sire": "2570@0",
  "children": [
    "10999@2",
    "11172@5",
    "11975@7",
    "12306@10",
    "12817@3",
    "12895@3",
    "14265@2",
    "16603@21"
  ],
  "hatched": true,
  "wrapped": false
}