{
  "id": 14257,
  "name": null,
  "generation": 15,
  "created_at": "2017-11-30T01:29:37.000Z",
  "birthday": "2017-11-30T00:00:00.000Z",
  "color": "mintgreen",
  "bio": "Ugh! My name's Kitty #14257. I once peed on John F. Kennedy Jr.'s cat. They had it coming. I put wasabi on everything. Like, everything: hot dogs, cantaloupe—everything! It's pawesome to meet you!",
  "language": "en",
  "matron": "9467@14",
  "sire": "10745@13",
  "children": [
    "55517@17"
  ],
  "hatched": true,
  "wrapped": false
}