{
  "id": 14374,
  "name": "⭐ Deep eye Kitten ⭐",
  "generation": 2,
  "created_at": "2017-11-30T01:53:01.000Z",
  "birthday": "2017-11-30T00:00:00.000Z",
  "color": "sizzurp",
  "bio": "What's up! I'm ⭐ Deep eye Kitten ⭐. My friends describe me as petulant and brilliant. It's not common knowledge, but my ancestry connects me to Mother Theresa. We can be friends, but keep the ultra purrsonal stuff to yourself, please.",
  "language": "en",
  "matron": "9227@1",
  "sire": "8192@1",
  "children": [
    "14846@3",
    "14961@3",
    "19610@3",
    "19779@3",
    "19864@3",
    "96386@3",
    "187559@3",
    "214329@3",
    "268362@3",
    "288023@5",
    "487540@5"
  ],
  "hatched": true,
  "wrapped": false
}