{
  "id": 16016,
  "name": "Gen 4 Rare Star ⭐",
  "generation": 4,
  "created_at": "2017-11-30T08:41:04.000Z",
  "birthday": "2017-11-30T00:00:00.000Z",
  "color": "mintgreen",
  "bio": "Uh, hi! I'm Gen 4 Rare Star ⭐. I'm a professional Private Dancer  and I love ice cream. When no one's home, I invite my pals over and we listen to Coldplay. We're so fur-tunate to have found each other!",
  "language": "en",
  "matron": "15936@3",
  "sire": "5866@2",
  "children": [
    "16060@5",
    "33469@6",
    "34263@5",
    "34564@6",
    "38543@5",
    "245780@5",
    "251904@8"
  ],
  "hatched": true,
  "wrapped": false
}