{
  "id": 12448,
  "name": "Caliwing",
  "generation": 14,
  "created_at": "2017-11-29T18:04:02.000Z",
  "birthday": "2017-11-29T00:00:00.000Z",
  "color": "chestnut",
  "bio": "Heyo! I'm Caliwing. I've never told anyone this, but I once clawed a dog. I once dreamed of being a Foreign Film Director. Now I can be found people-watching all day. I think you'll love me beclaws I have cattitude.",
  "language": "en",
  "matron": "8917@13",
  "sire": "4261@10",
  "children": [
    "14134@16",
    "14195@15",
    "22628@16"
  ],
  "hatched": true,
  "wrapped": false
}