{
  "id": 22153,
  "name": "LAPIS Tongue Choco X",
  "generation": 10,
  "created_at": "2017-12-01T09:52:08.000Z",
  "birthday": "2017-12-01T00:00:00.000Z",
  "color": "sizzurp",
  "bio": "Sup playa! I'm LAPIS Tongue Choco X. I'm often referred to as the Hermione Granger of the group. I was voted most likely to work at NASA in college. I can't wait to wake you up at 4am for seemingly no reason.",
  "language": "en",
  "matron": "20257@8",
  "sire": "21852@9",
  "children": [
    "26830@11",
    "26907@11",
    "30962@11",
    "48933@19",
    "88311@11",
    "116943@11",
    "234778@11"
  ],
  "hatched": true,
  "wrapped": false
}