{
  "id": 22611,
  "name": "G3 | Fluro",
  "generation": 3,
  "created_at": "2017-12-01T12:13:19.000Z",
  "birthday": "2017-12-01T00:00:00.000Z",
  "color": "strawberry",
  "bio": "*waves*! My name's G3 | Fluro. I once peed on Amelia Earhart's cat. They had it coming. I put ranch dressing on everything. Like, everything: hot dogs, lasagna—everything! I hope you like kitten around as much as I do!",
  "language": "en",
  "matron": "22094@2",
  "sire": "21138@2",
  "children": [
    "48945@4"
  ],
  "hatched": true,
  "wrapped": false
}