{
  "id": 2202,
  "name": "(￢_￢)瞄The world's 2202th",
  "generation": 0,
  "created_at": "2017-11-23T12:41:30.000Z",
  "birthday": "2017-11-23T00:00:00.000Z",
  "color": "sizzurp",
  "bio": "Mahalo! I'm (￢_￢)瞄The world's 2202th. I want to live in a world where people believe the world is flat. My great-great-great-great-great-great grandkitty lived with Confucius. Can't wait to eat salad with you!",
  "language": "en",
  "matron": null,
  "sire": null,
  "children": [

  ],
  "hatched": true,
  "wrapped": false
}