{
  "id": 2612,
  "name": "Gen 0",
  "generation": 0,
  "created_at": "2017-11-23T13:47:18.000Z",
  "birthday": "2017-11-23T00:00:00.000Z",
  "color": "mintgreen",
  "bio": "Shalom! Gen 0 here. I'm here to enjoy fighting the patriarchy and eating lasagna. I am 20% wizard, 9% Mad Scientist, and otherwise bad at math. I think you'll love me beclaws I have cattitude.",
  "language": "en",
  "matron": null,
  "sire": null,
  "children": [
    "21680@1",
    "21698@1",
    "26879@1",
    "26971@1",
    "27145@1",
    "31608@1",
    "35696@1",
    "74998@3",
    "211215@2",
    "229854@3",
    "258782@16",
    "284640@1",
    "325916@1",
    "376852@1",
    "421207@4",
    "460466@1",
    "482780@1",
    "503504@1",
    "528198@1",
    "617045@1",
    "624779@1",
    "651592@1",
    "669028@1",
    "711392@1",
    "730444@1",
    "741509@1",
    "742461@1",
    "760166@1",
    "777709@1",
    "789481@1",
    "798096@1",
    "819651@1",
    "854810@1",
    "867153@1",
    "878169@1",
    "927775@1",
    "964714@1",
    "1004500@1",
    "1023719@1",
    "1051976@1",
    "1072992@1",
    "1090687@1",
    "1105433@1",
    "1126644@1",
    "1144396@1",
    "1161056@1",
    "1187305@1",
    "1209301@1",
    "1209911@1",
    "1232644@1",
    "1266675@1",
    "1301008@1",
    "1301269@1",
    "1314274@1",
    "1367935@1",
    "1378495@1",
    "1399168@1",
    "1420536@1",
    "1435384@1",
    "1453107@1",
    "1469950@1",
    "1486349@1",
    "1511563@1",
    "1548202@1",
    "1674866@1",
    "1682411@1",
    "1751998@1",
    "1763529@1",
    "1769568@1",
    "1770335@1",
    "1781915@1",
    "1839793@1",
    "1872342@1",
    "1880223@1"
  ],
  "hatched": true,
  "wrapped": false
}