{
  "id": 7174,
  "name": "Felix Bonkers | White",
  "generation": 15,
  "created_at": "2017-11-25T16:59:26.000Z",
  "birthday": "2017-11-25T00:00:00.000Z",
  "color": "chestnut",
  "bio": "Hi-ya! I'm Felix Bonkers | White. In high school, I was voted school jock. It wasn't heavily publicized, but I once had a brief relationship with Felix the Cat. I hope you like kitten around as much as I do!",
  "language": "en",
  "matron": "6083@10",
  "sire": "6045@14",
  "children": [
    "9602@17",
    "11013@16",
    "268097@16"
  ],
  "hatched": true,
  "wrapped": false
}