{
  "id": 7953,
  "name": "Shadow - Gen15",
  "generation": 15,
  "created_at": "2017-11-26T06:13:34.000Z",
  "birthday": "2017-11-26T00:00:00.000Z",
  "color": "sizzurp",
  "bio": "Good day! I'm Shadow - Gen15. I'm a professional Private Dancer  and I love wet food. I once pawed at a gecko. I don't like to talk about it. Will you be the soy sauce to my marmalade?",
  "language": "en",
  "matron": "5197@11",
  "sire": "7152@14",
  "children": [
    "8965@16",
    "10865@16"
  ],
  "hatched": true,
  "wrapped": false
}