{
  "id": 23342,
  "name": "3444 Tongue Blood Raised #59",
  "generation": 1,
  "created_at": "2017-12-01T17:51:34.000Z",
  "birthday": "2017-12-01T00:00:00.000Z",
  "color": "strawberry",
  "bio": "Sup playa! 3444 Tongue Blood Raised #59 here. I'm here to enjoy grooming and breakdancing. I would give it all up to be on Oprah. This will be an amewsing friendship.",
  "kitty_type": "fancy",
  "is_fancy": true,
  "fancy_type": "DuCat",
  "language": "en",
  "matron": "22206@0",
  "sire": "22630@0",
  "children": [
    "24638@9",
    "24690@2",
    "25088@9",
    "1541830@2",
    "1542433@2",
    "1545726@2",
    "1550234@2",
    "1555180@2",
    "1563877@2",
    "1585634@2",
    "1600603@2",
    "1614628@2",
    "1628895@2",
    "1693447@2",
    "1697338@2",
    "1707604@2",
    "1724735@2",
    "1752875@2",
    "1769914@2",
    "1860787@2"
  ],
  "hatched": true,
  "wrapped": true,
  "fancy_ranking": 59,
  "fancy_limit": 10000,
  "fancy_remaining": 0
}