{
  "id": 77945,
  "name": "Duck maker",
  "generation": 10,
  "created_at": "2017-12-05T03:14:48.000Z",
  "birthday": "2017-12-05T00:00:00.000Z",
  "color": "sizzurp",
  "bio": "Heyo! I'm Duck maker. I'm a professional Dispensary Clerk and I love steak. I was voted biggest teacher's pet in college. Let's pawty!",
  "kitty_type": "fancy",
  "is_fancy": true,
  "fancy_type": "DuCat",
  "language": "en",
  "matron": "74775@9",
  "sire": "65406@8",
  "children": [
    "79753@12",
    "82698@11",
    "87012@11",
    "95588@11",
    "99701@11",
    "124648@11"
  ],
  "hatched": true,
  "wrapped": false,
  "fancy_ranking": 790,
  "fancy_limit": 10000,
  "fancy_remaining": 0
}