{
  "id": 167028,
  "name": "Two Duck Parents Virgin",
  "generation": 8,
  "created_at": "2017-12-09T00:32:04.000Z",
  "birthday": "2017-12-09T00:00:00.000Z",
  "color": "chestnut",
  "bio": "What's up! I'm Two Duck Parents Virgin. All you need to know about me is I hate apple pie with a passion. I put cinammon on everything. Like, everything: hot dogs, cereal—everything! I hope you like kitten around as much as I do!",
  "kitty_type": "fancy",
  "is_fancy": true,
  "fancy_type": "DuCat",
  "language": "en",
  "matron": "139515@7",
  "sire": "115290@7",
  "children": [
    "167930@9",
    "170104@9",
    "183801@9",
    "265205@9"
  ],
  "hatched": true,
  "wrapped": false,
  "fancy_ranking": 2084,
  "fancy_limit": 10000,
  "fancy_remaining": 0
}