{
  "id": 169546,
  "name": null,
  "generation": 12,
  "created_at": "2017-12-09T02:24:34.000Z",
  "birthday": "2017-12-09T00:00:00.000Z",
  "color": "chestnut",
  "bio": "Heyo! I'm Kitty #169546. My friends describe me as hairy and prickly. I am 28% elf, 88% Foreign Film Director, and otherwise bad at math. We're so fur-tunate to have found each other!",
  "kitty_type": "fancy",
  "is_fancy": true,
  "fancy_type": "DuCat",
  "language": "en",
  "matron": "57599@11",
  "sire": "164830@11",
  "children": [
    "175995@13",
    "190465@13"
  ],
  "hatched": true,
  "wrapped": false,
  "fancy_ranking": 2117,
  "fancy_limit": 10000,
  "fancy_remaining": 0
}