{
  "id": 240310,
  "name": null,
  "generation": 6,
  "created_at": "2017-12-11T10:40:26.000Z",
  "birthday": "2017-12-11T00:00:00.000Z",
  "color": "bubblegum",
  "bio": "Ugh! I'm Kitty #240310. I believe the world is flat. My friends describe me as \"preposterous.\" It's... accurate. This will be an amewsing friendship.",
  "kitty_type": "fancy",
  "is_fancy": true,
  "fancy_type": "DuCat",
  "language": "en",
  "matron": "224050@5",
  "sire": "190349@5",
  "children": [
    "240754@7",
    "241313@7"
  ],
  "hatched": true,
  "wrapped": false,
  "fancy_ranking": 3414,
  "fancy_limit": 10000,
  "fancy_remaining": 0
}