{
  "id": 346767,
  "name": null,
  "generation": 18,
  "created_at": "2017-12-17T02:39:26.000Z",
  "birthday": "2017-12-17T00:00:00.000Z",
  "color": "sizzurp",
  "bio": "*waves*! I'm Kitty #346767. In high school, I was voted school jock. I once made a gecko grimace. Let's pawty!",
  "kitty_type": "fancy",
  "is_fancy": true,
  "fancy_type": "DuCat",
  "language": "en",
  "matron": "285916@17",
  "sire": "241790@10",
  "children": [
    "361959@19",
    "1729890@19"
  ],
  "hatched": true,
  "wrapped": true,
  "fancy_ranking": 5852,
  "fancy_limit": 10000,
  "fancy_remaining": 0
}