{
  "id": 32903,
  "name": "g7 chartreux spock",
  "generation": 7,
  "created_at": "2017-12-02T22:14:30.000Z",
  "birthday": "2017-12-02T00:00:00.000Z",
  "color": "sizzurp",
  "bio": "*hissing noises*! I'm g7 chartreux spock. My friends describe me as preposterous and despicable. I once licked a dog. I don't like to talk about it. We can be friends, but keep the ultra purrsonal stuff to yourself, please.",
  "language": "en",
  "matron": "19730@6",
  "sire": "31679@5",
  "children": [

  ],
  "hatched": true,
  "wrapped": false
}