{
  "id": 314496,
  "name": "🦇DRACULA🦇",
  "generation": 4,
  "created_at": "2017-12-14T20:58:48.000Z",
  "birthday": "2017-12-14T00:00:00.000Z",
  "color": "strawberry",
  "bio": "Mahalo! 🦇DRACULA🦇 here. I'm here to enjoy slappin' da bass and hitting on yo' man. My great-great-great-great-great-great grandkitty lived with Nelson Mandela. I think you'll love me beclaws I have cattitude.",
  "kitty_type": "fancy",
  "is_fancy": true,
  "fancy_type": "Dracula",
  "language": "en",
  "matron": "119120@3",
  "sire": "234331@3",
  "children": [
    "341363@5",
    "343743@5",
    "347295@5",
    "358421@5",
    "360206@5",
    "371181@5",
    "377786@5",
    "382628@5",
    "388305@5",
    "395955@5",
    "409218@5"
  ],
  "hatched": true,
  "wrapped": false,
  "fancy_ranking": 482,
  "fancy_limit": 2000,
  "fancy_remaining": 0
}