{
  "id": 342963,
  "name": "Catilla the Hun",
  "generation": 4,
  "created_at": "2017-12-16T19:48:13.000Z",
  "birthday": "2017-12-16T00:00:00.000Z",
  "color": "strawberry",
  "bio": "Mahalo! I'm Catilla the Hun. I want to live in a world where people believe that one day cats will rule this planet. When my owner isn't watching, I steal their clutches and use them for litter paper. I'm not sorry. Maybe you and I can be partners in crime.",
  "kitty_type": "fancy",
  "is_fancy": true,
  "fancy_type": "Dracula",
  "language": "en",
  "matron": "335450@3",
  "sire": "342197@3",
  "children": [
    "343212@5",
    "343956@5",
    "389836@5",
    "396719@5",
    "397538@7",
    "436663@6",
    "495960@5",
    "497330@5",
    "501121@5",
    "504316@5",
    "511003@5",
    "542788@5",
    "550104@5",
    "603255@5",
    "784110@17"
  ],
  "hatched": true,
  "wrapped": false,
  "fancy_ranking": 615,
  "fancy_limit": 2000,
  "fancy_remaining": 0
}