{
  "id": 5228,
  "name": "William Catpurr",
  "generation": 6,
  "created_at": "2017-11-24T18:38:51.000Z",
  "birthday": "2017-11-24T00:00:00.000Z",
  "color": "mintgreen",
  "bio": "Shalom! I'm William Catpurr. I enjoy fighting for the people, reading garfield, and riding unicorns. I'm convinced that the world is flat. One day I'll prove it. I think you'll love me beclaws I have cattitude.",
  "language": "en",
  "matron": "3202@5",
  "sire": "3221@3",
  "children": [

  ],
  "hatched": true,
  "wrapped": true
}