{
  "id": 11529,
  "name": "StefLimey",
  "generation": 16,
  "created_at": "2017-11-29T08:54:43.000Z",
  "birthday": "2017-11-29T00:00:00.000Z",
  "color": "limegreen",
  "bio": "Hi-ya! I'm StefLimey. My friends describe me as hairy and ridiculous. I once dreamed of being a Spin Instructor . Now I can be found riverdancing all day. It's pawesome to meet you!",
  "language": "en",
  "matron": "8802@7",
  "sire": "7561@15",
  "children": [
    "16848@17",
    "31562@17",
    "40446@17"
  ],
  "hatched": true,
  "wrapped": false
}