{
  "id": 6212,
  "name": "Tabbytha Soren",
  "generation": 10,
  "created_at": "2017-11-25T03:00:38.000Z",
  "birthday": "2017-11-25T00:00:00.000Z",
  "color": "topaz",
  "bio": "Good morning! I'm Tabbytha Soren. I'm often referred to as the Neville Longbottom of the group. When no one's home, I invite my pals over and we listen to Mariah Carey. In time you'll learn how purrfect I am.",
  "language": "en",
  "matron": "5455@9",
  "sire": "4145@5",
  "children": [
    "6450@11",
    "6648@12",
    "11153@11"
  ],
  "hatched": true,
  "wrapped": false
}