{
  "id": 6272,
  "name": "Potocolor G15C6",
  "generation": 15,
  "created_at": "2017-11-25T03:28:36.000Z",
  "birthday": "2017-11-25T00:00:00.000Z",
  "color": "strawberry",
  "bio": "Yo! I'm Potocolor G15C6. My friends describe me as gorgeous and seductive. When no one's home, I invite my pals over and we listen to Beyoncé. Let's get busy!",
  "language": "en",
  "matron": "5018@6",
  "sire": "5746@14",
  "children": [
    "6973@16",
    "7078@16",
    "8279@16",
    "9232@16",
    "10042@16",
    "40682@16"
  ],
  "hatched": true,
  "wrapped": false
}