{
  "id": 6851,
  "name": "diamond laperm",
  "generation": 12,
  "created_at": "2017-11-25T09:56:33.000Z",
  "birthday": "2017-11-25T00:00:00.000Z",
  "color": "strawberry",
  "bio": "Shalom! I'm diamond laperm. I've never told anyone this, but I once cleaned a dog. It's not common knowledge, but my ancestry connects me to Confucius. I can't wait to wake you up at 4am for seemingly no reason.",
  "language": "en",
  "matron": "6595@11",
  "sire": "5187@11",
  "children": [
    "12863@16",
    "15561@14",
    "17877@13",
    "20288@16",
    "69106@20"
  ],
  "hatched": true,
  "wrapped": false
}