{
  "id": 6815,
  "name": "Clarice Noi",
  "generation": 11,
  "created_at": "2017-11-25T09:26:13.000Z",
  "birthday": "2017-11-25T00:00:00.000Z",
  "color": "strawberry",
  "bio": "Mahalo! I'm Clarice Noi. In high school, I was voted most likely to work at NASA. My great-great-great-great-great-great grandkitty lived with Confucius. I think you'll love me beclaws I have cattitude.",
  "language": "en",
  "matron": "4978@10",
  "sire": "6275@7",
  "children": [
    "7119@12",
    "7504@12",
    "8877@19",
    "100150@15"
  ],
  "hatched": true,
  "wrapped": false
}