{
  "id": 23086,
  "name": "G9 Mauveover, Saycheese",
  "generation": 9,
  "created_at": "2017-12-01T15:19:14.000Z",
  "birthday": "2017-12-01T00:00:00.000Z",
  "color": "limegreen",
  "bio": "Uh, hi! My name's G9 Mauveover, Saycheese. I once peed on Marie Antoinette's cat. They had it coming. I once dreamed of being a Foreign Film Director. Now I can be found pole dancing all day. We can be friends, but keep the ultra purrsonal stuff to yourself, please.",
  "language": "en",
  "matron": "18709@8",
  "sire": "19592@6",
  "children": [
    "70672@18",
    "870869@13"
  ],
  "hatched": true,
  "wrapped": false
}