{
  "id": 23750,
  "name": null,
  "generation": 17,
  "created_at": "2017-12-01T18:34:34.000Z",
  "birthday": "2017-12-01T00:00:00.000Z",
  "color": "mintgreen",
  "bio": "Yo! I'm Kitty #23750. I believe that one day cats will rule this planet. I once dreamed of being a Private Dancer . Now I can be found talking about how much I lift all day. I look forward to sweating through my feet with you.",
  "language": "en",
  "matron": "11455@16",
  "sire": "4937@13",
  "children": [
    "26091@18"
  ],
  "hatched": true,
  "wrapped": false
}