{
  "id": 25897,
  "name": "G15 | Sluggish | Scarletpeach",
  "generation": 15,
  "created_at": "2017-12-02T01:34:14.000Z",
  "birthday": "2017-12-02T00:00:00.000Z",
  "color": "mintgreen",
  "bio": "Ciao! My name's G15 | Sluggish | Scarletpeach. I once peed on Amelia Earhart's cat. They had it coming. My secret indulgence is cereal. Can you make my despicable dreams come true?",
  "language": "en",
  "matron": "20761@14",
  "sire": "20058@14",
  "children": [
    "28414@16",
    "32714@16",
    "44596@16",
    "69078@16"
  ],
  "hatched": true,
  "wrapped": false
}